{
  "fraction": "Eldar",
  "army": "Craftworld Mymeara",
  "version": "1.1",
  "release": "2022-04-01",
  "strategy": "Mymeara Armeen haben einen Strategiewert von 4.",
  "Initiative": "Aspect Warrior formations, Titans, Knights und the Avatar have an Initiative Rating of 1+. Alle anderen Verbände haben eine Initiative von 2+.",
  "specialRules": [
    "Avatar (Mymeara)",
    "May not Garrison (Mymeara)",
    "Farsight",
    "Hit und Run",
    "Webway Portal",
    "Independent Twins"
  ],
  "usage": [
    "The following army list allows you to field an army based on the Eldar Craftworld Mymeara."
  ],
  "units": [
    {
      "from": "EL.json",
      "units": [
        "Phoenix Lord",
        "Avatar",
        "Eldar Exarch",
        "Eldar Warlock",
        "Eldar Farseer",
        "Eldar Guardians",
        "Eldar Heavy Weapons Platform",
        "Support Weapons Platform",
        "Shadow Spectres",
        "Ghost Walkers",
        "Dire Avengers",
        "Fire Dragons",
        "Dark Reapers",
        "Howling Banshees",
        "Striking Scorpions",
        "Warp Spiders",
        "Wraithreapers",
        "Wasp Walker",
        "Wraithlord",
        "Wave Serpent",
        "Night Spinner",
        "Hornet",
        "Fire Prism",
        "Firestorm",
        "Warp Hunter",
        "Lynx",
        "Scorpion",
        "Cobra",
        "Wraithknights",
        "Revenant Titan",
        "Mymeara Phantom Titan"
      ],
      "unitRules": [
          "Lanze",
          "Schildbohrer",
          "Shield Disruptor",
          "Holofields (x)",
          "Heavy Armoured Vehicle (H-AV)"
      ]
    },
    {
      "from": "eldarNavy.json",
      "units": [
        "Nightshade Interceptor",
        "Hemlock Wraithfighters",
        "Wraithship",
        "Dragonship"
      ],
      "unitRules": [
      ]
    }
  ],
  "sections": [
    {
      "name": "Mymeara Craftworld Special",
      "formations": [
        {
          "name": "1 Avatar",
          "units": "Ein Avatar",
          "points": "0"
        },
        {
          "name": "0-1 Wraithgate",
          "units": "Ersetze eine objective marker in the Eldar player's half of the table mit einemWraithgate, this counts as an objective marker und a Webway Portal which may not be attacked oder damaged in any way. ",
          "points": 50
        }
      ]
    },
    {
      "name": "Craftworld Mymeara Hosts",
      "formations": [
        {
          "name": "0-1 Shadow Spectre Warhost",
          "units": "Acht Shadow Spectres",
          "Erweiterungen": [
            "Exarch, Phoenix Lord"
          ],
          "points": 300
        },
        {
          "name": "Aspect Warrior Warhost",
          "units": "Zwei Wave Serpents und vier Aspect Warrior units chosen from the following: Dark Reapers, Dire Avengers, Fire Dragons, Howling Banshees, Striking Scorpions, Warp Spiders",
          "Erweiterungen": [
            "Exarch"
          ],
          "points": 225
        },
        {
          "name": "Guardian Warhost",
          "units": "Fünf Guardians, eine Warlock, drei Wave Serpents",
          "Erweiterungen": [
            "Farseer"
          ],
          "points": 250
        }
      ]
    },
    {
      "name": "Craftworld Mymeara Troupes",
      "description": " Bis zu zwei für jeweils 'Mymeara Hosts' taken",
      "formations": [
        {
          "name": "Wasp Walkers",
          "units": "Vier Wasp Walkers",
          "Erweiterungen": [
          ],
          "points": 150
        },
        {
          "name": "Heavy Wraithguard",
          "units": "Drei Heavy Wraithguard",
          "Erweiterungen": [
            "Füge drei Wave Serpents: 75 Points",
            "Firestorm",
            "Füge zwei Wraithlords und eine Spiritseer: 125 Punkte"
          ],
          "points": 200
        },
        {
          "name": "Hornets",
          "units": "Vier Hornets",
          "Erweiterungen": [
            "Füge bis zu zwei Hornets: 35 Punkte jeweils"
          ],
          "points": 175
        },
        {
          "name": "Night Spinner Troupe",
          "units": "Drei Night Spinners",
          "Erweiterungen": [
          ],
          "points": 175
        },
        {
          "name": "Hunters of Vaul",
          "units": "Fünf Warp Hunters",
          "Erweiterungen": [
            "Firestorm"
          ],
          "points": 300
        },
        {
          "name": "Fire Prism Troupe ",
          "units": "Drei Fire Prisms",
          "Erweiterungen": [
          ],
          "points": 250
        },
        {
          "name": "Armour of Vaul",
          "units": "Zwei Lynx",
          "Erweiterungen": [
          ],
          "points": 325
        },
        {
          "name": "Engine of Vaul",
          "units": "Any eine of the following units: Cobra, Scorpion",
          "Erweiterungen": [
            "Füge bis zu any zwei of the following units für 200 Punkte jeweils: Cobra, Scorpion"
          ],
          "points": 250
        }
      ]
    },
    {
      "name": "Craftworld Mymeara Aircraft, Spacecraft und Titans",
      "description": " Bis zu einem Drittel der verfügbaren Punkte dürfen für these formations",
      "formations": [
        {
          "name": "Nightshade Aerie",
          "units": "Zwei Nightshade Interceptors",
          "Erweiterungen": [
          ],
          "points": 225
        },
        {
          "name": "Hemlock Wraithfighter Aerie",
          "units": "Zwei Hemlock Wraithfighters",
          "Erweiterungen": [
          ],
          "points": 225
        },
        {
          "name": "Wraithknights",
          "units": "Drei Wraithknights",
          "Erweiterungen": [
          ],
          "points": 325
        },
        {
          "name": "Revenants",
          "units": "Zwei Revenant Titans",
          "Erweiterungen": [
            "Independent Twins: 50 Punkte"
          ],
          "points": 625
        },
        {
          "name": "0-1 Spacecraft",
          "units": "Ein Wraithship",
          "extraUnits": [
            "Ersetze mit einemDragonship: 125 Points"
          ],
          "points": 175
        }
      ]
    }
  ],
  "Erweiterungen": {
    "title": "Erweiterungen",
    "description": "Jeweils upgrade may be taken once pro formation",
    "items": [
      {
        "name": "0-1 Phoenix Lord",
        "description": "Ersetze opne Eldar Exarch mit einemEldar Phoenix Lord character",
        "points": "25 Punkte"
      },
      {
        "name": "Exarch",
        "description": "Füge bis zu zwei Eldar Exarch characters to Eldar Aspect Warrior units",
        "points": "50 Punkte jeweils"
      },
      {
        "name": "Firestorm",
        "description": "Ersetze eine Falcon mit einemFirestorm",
        "points": "Free"
      },
      {
        "name": "Farseer",
        "description": "Füge eine Farseer character to a unit of Guardians",
        "points": "25 Punkte"
      }
    ]
  }
}
